AUTHORS.rst
CONTRIBUTING.rst
HISTORY.rst
LICENSE
MANIFEST.in
README.rst
setup.cfg
setup.py
metevents/__init__.py
metevents/events.py
metevents/periods.py
metevents/utilities.py
metevents.egg-info/PKG-INFO
metevents.egg-info/SOURCES.txt
metevents.egg-info/dependency_links.txt
metevents.egg-info/entry_points.txt
metevents.egg-info/not-zip-safe
metevents.egg-info/requires.txt
metevents.egg-info/top_level.txt
tests/__init__.py
tests/test_events.py
tests/test_periods.py
tests/test_utilities.py
tests/data/mocks/flv.csv