Metadata-Version: 2.1
Name: metevents
Version: 0.3.0
Summary: Timeseries Analysis for Meteorlogical Events (metevents)
Home-page: https://github.com/M3Works/metevents
Author: M3Works
Author-email: m3worksllc@gmail.com
License: BSD license
Keywords: metevents
Platform: UNKNOWN
Classifier: Development Status :: 2 - Pre-Alpha
Classifier: Intended Audience :: Developers
Classifier: License :: OSI Approved :: BSD License
Classifier: Natural Language :: English
Classifier: Programming Language :: Python :: 3
Classifier: Programming Language :: Python :: 3.7
Classifier: Programming Language :: Python :: 3.8
Classifier: Programming Language :: Python :: 3.9
Requires-Python: >=3.7
License-File: LICENSE
License-File: AUTHORS.rst
